{
  "Data": "2025-09-21T22:03:36.9580261Z",
  "Clientes": [
    {
      "Id": 4,
      "Nome": "Teste1",
      "Email": "teste",
      "Cpf": "12356789011",
      "DataNascimento": "2002-09-21T00:00:00",
      "RendaMensal": 1000,
      "ValorDisponivel": 100,
      "PerfilRisco": 1,
      "ObjetivoPrincipal": 1,
      "PrazoInvestimentoMeses": 0,
      "DataCadastro": "2025-09-21T17:23:48.4361137",
      "Ativo": false,
      "CarteirasRecomendadas": null,
      "HistoricoInvestimentos": null
    },
    {
      "Id": 8,
      "Nome": "Teste2",
      "Email": "teste2",
      "Cpf": "12356789012",
      "DataNascimento": "2002-09-21T00:00:00",
      "RendaMensal": 1000,
      "ValorDisponivel": 100,
      "PerfilRisco": 1,
      "ObjetivoPrincipal": 1,
      "PrazoInvestimentoMeses": 0,
      "DataCadastro": "2025-09-21T17:39:24.9839408",
      "Ativo": false,
      "CarteirasRecomendadas": null,
      "HistoricoInvestimentos": null
    },
    {
      "Id": 1,
      "Nome": "Jo\u00E3o Silva Santos",
      "Email": "joao.silva@email.com",
      "Cpf": "12345678901",
      "DataNascimento": "1985-03-15T00:00:00",
      "RendaMensal": 8000,
      "ValorDisponivel": 50000,
      "PerfilRisco": 2,
      "ObjetivoPrincipal": 3,
      "PrazoInvestimentoMeses": 36,
      "DataCadastro": "2025-09-21T13:25:03",
      "Ativo": true,
      "CarteirasRecomendadas": null,
      "HistoricoInvestimentos": null
    },
    {
      "Id": 2,
      "Nome": "Maria Oliveira Costa",
      "Email": "maria.costa@email.com",
      "Cpf": "98765432100",
      "DataNascimento": "1990-07-22T00:00:00",
      "RendaMensal": 5500,
      "ValorDisponivel": 25000,
      "PerfilRisco": 1,
      "ObjetivoPrincipal": 5,
      "PrazoInvestimentoMeses": 12,
      "DataCadastro": "2025-09-21T13:25:03",
      "Ativo": true,
      "CarteirasRecomendadas": null,
      "HistoricoInvestimentos": null
    },
    {
      "Id": 3,
      "Nome": "Carlos Eduardo Lima",
      "Email": "carlos.lima@email.com",
      "Cpf": "11122233344",
      "DataNascimento": "1978-11-08T00:00:00",
      "RendaMensal": 12000,
      "ValorDisponivel": 100000,
      "PerfilRisco": 3,
      "ObjetivoPrincipal": 4,
      "PrazoInvestimentoMeses": 120,
      "DataCadastro": "2025-09-21T13:25:03",
      "Ativo": true,
      "CarteirasRecomendadas": null,
      "HistoricoInvestimentos": null
    }
  ],
  "Ativos": [
    {
      "Id": 13,
      "Codigo": "TESTE1",
      "Nome": "teste",
      "Descricao": "teste",
      "TipoAtivo": 1,
      "RentabilidadeEsperada": 0,
      "NivelRisco": 1,
      "LiquidezDias": 0,
      "ValorMinimo": 0,
      "TaxaAdministracao": 0,
      "AtivoSistema": false,
      "DataCriacao": "2025-09-21T17:11:45.341689",
      "ItensCarteira": null,
      "VariaveisMacroeconomicas": null
    },
    {
      "Id": 14,
      "Codigo": "TESTE",
      "Nome": "teste",
      "Descricao": "teste",
      "TipoAtivo": 1,
      "RentabilidadeEsperada": 0,
      "NivelRisco": 1,
      "LiquidezDias": 0,
      "ValorMinimo": 0,
      "TaxaAdministracao": 0,
      "AtivoSistema": false,
      "DataCriacao": "2025-09-21T17:40:53.7210523",
      "ItensCarteira": null,
      "VariaveisMacroeconomicas": null
    },
    {
      "Id": 1,
      "Codigo": "TESOURO_SELIC",
      "Nome": "Tesouro Selic 2029",
      "Descricao": "T\u00EDtulo p\u00FAblico p\u00F3s-fixado indexado \u00E0 taxa Selic, ideal para reserva de emerg\u00EAncia",
      "TipoAtivo": 1,
      "RentabilidadeEsperada": 13.75,
      "NivelRisco": 1,
      "LiquidezDias": 1,
      "ValorMinimo": 30,
      "TaxaAdministracao": 0,
      "AtivoSistema": true,
      "DataCriacao": "2025-09-21T13:24:50",
      "ItensCarteira": null,
      "VariaveisMacroeconomicas": null
    },
    {
      "Id": 2,
      "Codigo": "TESOURO_IPCA_29",
      "Nome": "Tesouro IPCA\u002B 2029",
      "Descricao": "T\u00EDtulo p\u00FAblico h\u00EDbrido que protege da infla\u00E7\u00E3o com juros reais",
      "TipoAtivo": 1,
      "RentabilidadeEsperada": 6.5,
      "NivelRisco": 1,
      "LiquidezDias": 1,
      "ValorMinimo": 30,
      "TaxaAdministracao": 0,
      "AtivoSistema": true,
      "DataCriacao": "2025-09-21T13:24:50",
      "ItensCarteira": null,
      "VariaveisMacroeconomicas": null
    },
    {
      "Id": 3,
      "Codigo": "TESOURO_PREF_27",
      "Nome": "Tesouro Prefixado 2027",
      "Descricao": "T\u00EDtulo p\u00FAblico com taxa fixa, ideal para queda de juros",
      "TipoAtivo": 1,
      "RentabilidadeEsperada": 12.5,
      "NivelRisco": 2,
      "LiquidezDias": 1,
      "ValorMinimo": 30,
      "TaxaAdministracao": 0,
      "AtivoSistema": true,
      "DataCriacao": "2025-09-21T13:24:50",
      "ItensCarteira": null,
      "VariaveisMacroeconomicas": null
    },
    {
      "Id": 4,
      "Codigo": "CDB_INTER",
      "Nome": "CDB Banco Inter",
      "Descricao": "Certificado de Dep\u00F3sito Banc\u00E1rio com liquidez di\u00E1ria",
      "TipoAtivo": 1,
      "RentabilidadeEsperada": 13,
      "NivelRisco": 1,
      "LiquidezDias": 1,
      "ValorMinimo": 100,
      "TaxaAdministracao": 0,
      "AtivoSistema": true,
      "DataCriacao": "2025-09-21T13:24:50",
      "ItensCarteira": null,
      "VariaveisMacroeconomicas": null
    },
    {
      "Id": 5,
      "Codigo": "LCI_SANTANDER",
      "Nome": "LCI Santander",
      "Descricao": "Letra de Cr\u00E9dito Imobili\u00E1rio isenta de Imposto de Renda",
      "TipoAtivo": 1,
      "RentabilidadeEsperada": 12.5,
      "NivelRisco": 1,
      "LiquidezDias": 90,
      "ValorMinimo": 1000,
      "TaxaAdministracao": 0,
      "AtivoSistema": true,
      "DataCriacao": "2025-09-21T13:24:50",
      "ItensCarteira": null,
      "VariaveisMacroeconomicas": null
    },
    {
      "Id": 6,
      "Codigo": "VALE3",
      "Nome": "Vale S.A.",
      "Descricao": "A\u00E7\u00F5es da maior mineradora do Brasil, grande exposi\u00E7\u00E3o a commodities",
      "TipoAtivo": 2,
      "RentabilidadeEsperada": 15,
      "NivelRisco": 3,
      "LiquidezDias": 2,
      "ValorMinimo": 50,
      "TaxaAdministracao": 0,
      "AtivoSistema": true,
      "DataCriacao": "2025-09-21T13:24:50",
      "ItensCarteira": null,
      "VariaveisMacroeconomicas": null
    },
    {
      "Id": 7,
      "Codigo": "PETR4",
      "Nome": "Petrobras PN",
      "Descricao": "A\u00E7\u00F5es preferenciais da Petrobras, exposi\u00E7\u00E3o ao setor de energia",
      "TipoAtivo": 2,
      "RentabilidadeEsperada": 18,
      "NivelRisco": 3,
      "LiquidezDias": 2,
      "ValorMinimo": 30,
      "TaxaAdministracao": 0,
      "AtivoSistema": true,
      "DataCriacao": "2025-09-21T13:24:50",
      "ItensCarteira": null,
      "VariaveisMacroeconomicas": null
    },
    {
      "Id": 8,
      "Codigo": "ITUB4",
      "Nome": "Ita\u00FA Unibanco PN",
      "Descricao": "A\u00E7\u00F5es do maior banco privado do Brasil, setor financeiro",
      "TipoAtivo": 2,
      "RentabilidadeEsperada": 12,
      "NivelRisco": 2,
      "LiquidezDias": 2,
      "ValorMinimo": 25,
      "TaxaAdministracao": 0,
      "AtivoSistema": true,
      "DataCriacao": "2025-09-21T13:24:50",
      "ItensCarteira": null,
      "VariaveisMacroeconomicas": null
    },
    {
      "Id": 9,
      "Codigo": "WEGE3",
      "Nome": "WEG S.A.",
      "Descricao": "A\u00E7\u00F5es de empresa de equipamentos el\u00E9tricos, crescimento sustent\u00E1vel",
      "TipoAtivo": 2,
      "RentabilidadeEsperada": 20,
      "NivelRisco": 2,
      "LiquidezDias": 2,
      "ValorMinimo": 40,
      "TaxaAdministracao": 0,
      "AtivoSistema": true,
      "DataCriacao": "2025-09-21T13:24:50",
      "ItensCarteira": null,
      "VariaveisMacroeconomicas": null
    },
    {
      "Id": 10,
      "Codigo": "FUNDO_DI_BTG",
      "Nome": "BTG Pactual Yield DI FI",
      "Descricao": "Fundo conservador que acompanha 100% do CDI",
      "TipoAtivo": 3,
      "RentabilidadeEsperada": 13.5,
      "NivelRisco": 1,
      "LiquidezDias": 1,
      "ValorMinimo": 500,
      "TaxaAdministracao": 0.5,
      "AtivoSistema": true,
      "DataCriacao": "2025-09-21T13:24:50",
      "ItensCarteira": null,
      "VariaveisMacroeconomicas": null
    },
    {
      "Id": 11,
      "Codigo": "FUNDO_MULTI_XP",
      "Nome": "XP Allocation FI Multi",
      "Descricao": "Fundo multimercado moderado com gest\u00E3o ativa",
      "TipoAtivo": 3,
      "RentabilidadeEsperada": 16,
      "NivelRisco": 2,
      "LiquidezDias": 30,
      "ValorMinimo": 1000,
      "TaxaAdministracao": 1.2,
      "AtivoSistema": true,
      "DataCriacao": "2025-09-21T13:24:50",
      "ItensCarteira": null,
      "VariaveisMacroeconomicas": null
    },
    {
      "Id": 12,
      "Codigo": "FUNDO_ACOES_BRAD",
      "Nome": "Bradesco FIA Dividendos",
      "Descricao": "Fundo de a\u00E7\u00F5es focado em empresas pagadoras de dividendos",
      "TipoAtivo": 3,
      "RentabilidadeEsperada": 22,
      "NivelRisco": 3,
      "LiquidezDias": 5,
      "ValorMinimo": 500,
      "TaxaAdministracao": 2,
      "AtivoSistema": true,
      "DataCriacao": "2025-09-21T13:24:50",
      "ItensCarteira": null,
      "VariaveisMacroeconomicas": null
    }
  ],
  "Variaveis": [
    {
      "Id": 1,
      "Nome": "Taxa Selic",
      "Codigo": "SELIC",
      "Descricao": "Taxa b\u00E1sica de juros da economia brasileira definida pelo Copom",
      "ValorAtual": 14.0835,
      "ValorAnterior": 13.8656,
      "DataAtualizacao": "2025-09-21T16:37:42.1275643",
      "DataReferencia": "2025-09-21T13:24:35",
      "UnidadeMedida": "%",
      "FonteDados": "BACEN",
      "Tendencia": "ESTAVEL",
      "ImpactoInvestimentos": "Alta influ\u00EAncia em t\u00EDtulos de renda fixa, especialmente Tesouro Selic",
      "Ativa": true,
      "AtivosAfetados": null
    },
    {
      "Id": 2,
      "Nome": "IPCA",
      "Codigo": "IPCA",
      "Descricao": "\u00CDndice Nacional de Pre\u00E7os ao Consumidor Amplo - Meta de infla\u00E7\u00E3o",
      "ValorAtual": 4.62,
      "ValorAnterior": 5.19,
      "DataAtualizacao": "2025-09-21T13:24:35",
      "DataReferencia": "2025-09-21T13:24:35",
      "UnidadeMedida": "%",
      "FonteDados": "IBGE",
      "Tendencia": "BAIXA",
      "ImpactoInvestimentos": "Refer\u00EAncia para investimentos inflacion\u00E1rios como Tesouro IPCA\u002B",
      "Ativa": true,
      "AtivosAfetados": null
    },
    {
      "Id": 3,
      "Nome": "CDI",
      "Codigo": "CDI",
      "Descricao": "Certificado de Dep\u00F3sito Interbanc\u00E1rio - Taxa de refer\u00EAncia do mercado",
      "ValorAtual": 13.65,
      "ValorAnterior": 13.15,
      "DataAtualizacao": "2025-09-21T13:24:35",
      "DataReferencia": "2025-09-21T13:24:35",
      "UnidadeMedida": "%",
      "FonteDados": "CETIP",
      "Tendencia": "ESTAVEL",
      "ImpactoInvestimentos": "Base para c\u00E1lculo de rentabilidade de CDBs, LCIs e fundos DI",
      "Ativa": true,
      "AtivosAfetados": null
    },
    {
      "Id": 4,
      "Nome": "D\u00F3lar Americano",
      "Codigo": "USD",
      "Descricao": "Taxa de c\u00E2mbio Real/D\u00F3lar americano",
      "ValorAtual": 5.15,
      "ValorAnterior": 5.05,
      "DataAtualizacao": "2025-09-21T13:24:35",
      "DataReferencia": "2025-09-21T13:24:35",
      "UnidadeMedida": "R$",
      "FonteDados": "BACEN",
      "Tendencia": "ALTA",
      "ImpactoInvestimentos": "Impacta fundos cambiais, a\u00E7\u00F5es de exportadoras e investimentos internacionais",
      "Ativa": true,
      "AtivosAfetados": null
    },
    {
      "Id": 5,
      "Nome": "Ibovespa",
      "Codigo": "IBOV",
      "Descricao": "\u00CDndice da Bolsa de Valores de S\u00E3o Paulo",
      "ValorAtual": 125430.5,
      "ValorAnterior": 124890.2,
      "DataAtualizacao": "2025-09-21T13:24:35",
      "DataReferencia": "2025-09-21T13:24:35",
      "UnidadeMedida": "pontos",
      "FonteDados": "B3",
      "Tendencia": "ALTA",
      "ImpactoInvestimentos": "Principal refer\u00EAncia para fundos de a\u00E7\u00F5es e investimentos em bolsa",
      "Ativa": true,
      "AtivosAfetados": null
    }
  ]
}